{"chunk_definitions":[{"row":14,"row_count":1,"visible":true,"expansion_state":0,"options":{"engine":"r","label":"unnamed-chunk-19"},"document_id":"B6C220BD","chunk_id":"c074lwuuof8qv","chunk_label":"unnamed-chunk-1"},{"row":26,"row_count":1,"visible":true,"expansion_state":0,"options":{"engine":"r","label":"unnamed-chunk-23"},"document_id":"B6C220BD","chunk_id":"cxr2cuzrnngek","chunk_label":"unnamed-chunk-2"},{"row":38,"row_count":1,"visible":true,"expansion_state":0,"options":{"engine":"r","label":"unnamed-chunk-24"},"document_id":"B6C220BD","chunk_id":"cexbs5dv8j85n","chunk_label":"unnamed-chunk-3"},{"row":44,"row_count":1,"visible":true,"expansion_state":0,"options":{"engine":"r","label":"unnamed-chunk-25"},"document_id":"B6C220BD","chunk_id":"c0a00wy7ssjto","chunk_label":"unnamed-chunk-4"},{"row":136,"row_count":1,"visible":true,"expansion_state":0,"options":{"engine":"r","label":"unnamed-chunk-3"},"document_id":"E2469E5C","chunk_id":"cxoaugmpf2mhw","chunk_label":"unnamed-chunk-14"},{"row":148,"row_count":1,"visible":true,"expansion_state":0,"options":{"engine":"r","label":"unnamed-chunk-4"},"document_id":"E2469E5C","chunk_id":"c2riney9c8pmu","chunk_label":"unnamed-chunk-15"}],"doc_write_time":1677479159}